teem/__init__.py
teem-0.0.1.dist-info/LICENSE
teem-0.0.1.dist-info/METADATA
teem-0.0.1.dist-info/WHEEL
teem-0.0.1.dist-info/top_level.txt
teem-0.0.1.dist-info/RECORD
