Metadata-Version: 2.1
Name: teem
Version: 0.0.1
Summary: teem: a powerful tensorizing toolkit based on Pytorch
Home-page: https://github.com/tnbar/teem
Author: Yu
Maintainer: Yu
License: MIT
Platform: any
License-File: LICENSE
